gaia2_pytorch/__init__.py
gaia2_pytorch/gaia2.py
gaia2_pytorch/tensor_typing.py
gaia2_pytorch-0.0.33.dist-info/METADATA
gaia2_pytorch-0.0.33.dist-info/WHEEL
gaia2_pytorch-0.0.33.dist-info/licenses/LICENSE
gaia2_pytorch-0.0.33.dist-info/RECORD
