Metadata-Version: 2.4
Name: gaia2-pytorch
Version: 0.0.33
Summary: Gaia2 - Pytorch
Project-URL: Homepage, https://pypi.org/project/gaia2-pytorch/
Project-URL: Repository, https://github.com/lucidrains/gaia2-pytorch
Author-email: Phil Wang <lucidrains@gmail.com>
License: MIT License
License-File: LICENSE
Keywords: artificial intelligence,autonomous driving,deep learning,flow matching,transformers
Classifier: Development Status :: 4 - Beta
Classifier: Intended Audience :: Developers
Classifier: License :: OSI Approved :: MIT License
Classifier: Programming Language :: Python :: 3.9
Classifier: Topic :: Scientific/Engineering :: Artificial Intelligence
Requires-Python: >=3.9
Requires-Dist: einops>=0.8.1
Requires-Dist: einx>=0.3.0
Requires-Dist: ema-pytorch
Requires-Dist: hyper-connections>=0.2.1
Requires-Dist: jaxtyping
Requires-Dist: rotary-embedding-torch>=0.8.7
Requires-Dist: torch>=2.4
Requires-Dist: torchdiffeq
Requires-Dist: torchvision
Provides-Extra: examples
Provides-Extra: test
Requires-Dist: pytest; extra == 'test'
